{
  "niacinamide": {"category":"active","benefits":["oil control","redness","acne"],"comedogenic_rating":1,"irritation_risk":"low"},
  "glycerin": {"category":"humectant","benefits":["hydration"],"comedogenic_rating":0,"irritation_risk":"none"},
  "hyaluronic acid": {"category":"humectant","benefits":["hydration","plumping"],"comedogenic_rating":0,"irritation_risk":"none"},
  "salicylic acid": {"category":"exfoliant","benefits":["acne","oil control"],"comedogenic_rating":0,"irritation_risk":"medium"},
  "benzoyl peroxide": {"category":"acne treatment","benefits":["kills acne bacteria"],"comedogenic_rating":0,"irritation_risk":"high"},
  "retinol": {"category":"retinoid","benefits":["anti-aging","acne"],"comedogenic_rating":0,"irritation_risk":"high"},
  "vitamin c": {"category":"antioxidant","benefits":["brightening","hyperpigmentation"],"comedogenic_rating":0,"irritation_risk":"medium"},
  "ceramides": {"category":"barrier repair","benefits":["barrier repair","hydration"],"comedogenic_rating":0,"irritation_risk":"none"},
  "fragrance": {"category":"irritant","benefits":[],"comedogenic_rating":0,"irritation_risk":"high"},
  "parfum": {"category":"irritant","benefits":[],"comedogenic_rating":0,"irritation_risk":"high"},
  "alcohol denat": {"category":"solvent","benefits":[],"comedogenic_rating":0,"irritation_risk":"high"},
  "dimethicone": {"category":"silicone","benefits":["skin smoothing"],"comedogenic_rating":1,"irritation_risk":"low"},
  "panthenol": {"category":"soothing","benefits":["hydration","barrier support"],"comedogenic_rating":0,"irritation_risk":"none"},
  "allantoin": {"category":"soothing","benefits":["calming","healing"],"comedogenic_rating":0,"irritation_risk":"none"}
}
